{"balances": {"(2020, 11, 20)": "109.99", "(2021, 4, 3)": "-5652.33", "(2020, 12, 31)": "-1550.33", "(2020, 11, 27)": "-540.33", "(2021, 4, 1)": "-5598.33", "(2020, 12, 3)": "-1581.33", "(2021, 1, 1)": "-2537.33", "(2021, 3, 3)": "-4642.33", "(2020, 12, 1)": "-1527.33", "(2021, 2, 1)": "-3547.33", "(2021, 3, 1)": "-4588.33", "(2021, 2, 3)": "-3601.33", "(2021, 1, 31)": "-2560.33", "(2021, 1, 3)": "-2591.33", "(2021, 3, 31)": "-4611.33"}, "users": ["rane"], "name": "Personal", "accounts": {"kleptopalace": {}, "jingleberries": {}, "beergogglers": {"transactions": {"1605232446_2020-11-1": "988.0"}}, "my dog": {}, "fartland": {}, "little shitheads": {}, "smashfactory": {}, "feptards": {}, "ACS": {"transactions": {"1605025725_2020-11-3": "600.32", "1605684628_2020-11-3": "100.0"}}, "your mom": {}, "bin ladens": {}}, "balance": "700", "tasks": {"hidden_repetition": {}, "repetition": [{"account": "feptards", "amount": "31", "id": 1605229404, "details": "every 31st get some chedda", "repetition_value": 31, "color": "#3EB34F", "repetition_type": "m", "repetition_subtype": "m", "credit_debit": "credit"}, {"account": "beergogglers", "amount": "987", "id": 1605232446, "details": "&nbsp;", "repetition_value": 1, "color": "#808080", "repetition_type": "m", "repetition_subtype": null, "credit_debit": "debit"}, {"account": "ACS", "amount": "54.00", "id": 1605684628, "details": "MONTHLY INTERNET", "repetition_value": 3, "color": "#A020F0", "repetition_type": "m", "repetition_subtype": "", "credit_debit": "debit"}], "normal": {"2020": {"11": {"11": [{"account": "fluffers", "amount": "44.18", "id": 1605683145, "details": "supplies", "color": "#FF4848", "credit_debit": "debit"}], "20": [{"account": "1", "amount": "590.01", "id": 1605210292, "details": "casino losings", "color": "#FF4848", "credit_debit": "debit"}], "27": [{"account": "fartland", "amount": "650.32", "id": 1605684672, "details": "&nbsp;", "color": "#3EB34F", "credit_debit": "credit"}], "10": [{"account": "your mom", "amount": "69.69", "id": 1605683124, "details": "&nbsp;", "color": "#3EB34F", "credit_debit": "credit"}, {"account": "ACS", "amount": "54.00", "id": 1605684605, "details": "this<br>is<br>many<br>lines<br>of<br>text<br>right<br>here", "color": "#A020F0", "credit_debit": "debit"}], "12": [{"account": "1", "amount": "15.99", "id": 1605212213, "details": "stolen funds", "color": "#FF4848", "credit_debit": "debit"}], "17": [{"account": "my dog", "amount": "1600.00", "id": 1605215146, "details": "he needed a new collar and a friend", "color": "#FF4848", "credit_debit": "debit"}]}}}}}
